pyMesa/__init__.py
pyMesa/pyMesaUtils.py
pyMesa-2.0.1.dist-info/METADATA
pyMesa-2.0.1.dist-info/WHEEL
pyMesa-2.0.1.dist-info/top_level.txt
pyMesa-2.0.1.dist-info/RECORD
