Metadata-Version: 2.1
Name: pyMesa
Version: 2.0.1
Summary: "Python bindings for MESA (Modules for Experiments in Stellar Astrophysics)"
Home-page: https://github.com/rjfarmer/pyMesa
Author: Robert Farmer
Author-email: robert.j.farmer37@gmail.com
License: GPLv2+
Platform: unix
Platform: linux
Classifier: Programming Language :: Python :: 3
Classifier: Programming Language :: Python :: 3 :: Only
Classifier: Programming Language :: Python :: 3.7
Classifier: Programming Language :: Python :: 3.8
Classifier: Programming Language :: Python :: 3.9
Classifier: Programming Language :: Python :: 3.10
Classifier: Programming Language :: Python :: 3.11
Requires-Python: >=3.7
